{
    "name": "hitmonlee",
    "id": 106,
    "height": "4'11\"",
    "weight": "109.8 lbs",
    "types": [
        "fighting"
    ],
    "stats": {
        "hp": 50,
        "attack": 120,
        "defense": 53,
        "sp. attack": 35,
        "sp. defense": 110,
        "speed": 87
    },
    "abilities": [
        {
            "name": "limber",
            "effect": "Prevents paralysis.",
            "hidden": false
        },
        {
            "name": "reckless",
            "effect": "Strengthens recoil moves to 1.2\u00d7 their power.",
            "hidden": false
        },
        {
            "name": "unburden",
            "effect": "Doubles Speed upon using or losing a held item.",
            "hidden": true
        }
    ]
}