{
    "name": "crobat",
    "id": 169,
    "height": "5'11\"",
    "weight": "165.3 lbs",
    "types": [
        "poison",
        "flying"
    ],
    "stats": {
        "hp": 85,
        "attack": 90,
        "defense": 80,
        "sp. attack": 70,
        "sp. defense": 80,
        "speed": 130
    },
    "abilities": [
        {
            "name": "inner-focus",
            "effect": "Prevents flinching.",
            "hidden": false
        },
        {
            "name": "infiltrator",
            "effect": "Bypasses light screen, reflect, and safeguard.",
            "hidden": true
        }
    ]
}