{
    "id": 187,
    "name": "hoppip",
    "height": "1'4\"",
    "weight": "1.1 lbs",
    "types": [
        "grass",
        "flying"
    ],
    "stats": {
        "total": 250,
        "hp": 35,
        "attack": 35,
        "defense": 40,
        "sp. attack": 35,
        "sp. defense": 55,
        "speed": 50
    },
    "abilities": [
        {
            "name": "chlorophyll",
            "effect": "Doubles Speed during strong sunlight.",
            "hidden": false
        },
        {
            "name": "leaf-guard",
            "effect": "Protects against major status ailments during strong sunlight.",
            "hidden": false
        },
        {
            "name": "infiltrator",
            "effect": "Bypasses light screen, reflect, and safeguard.",
            "hidden": true
        }
    ],
    "type_chart": {
        "4": [
            "ice"
        ],
        "2": [
            "flying",
            "poison",
            "fire",
            "rock"
        ],
        "1": [
            "psychic",
            "normal",
            "ghost",
            "dragon",
            "dark",
            "steel",
            "fairy",
            "electric",
            "bug"
        ],
        "1/2": [
            "water",
            "fighting"
        ],
        "1/4": [
            "grass"
        ],
        "0": []
    }
}