{
    "id": 218,
    "name": "slugma",
    "height": "2'4\"",
    "weight": "77.2 lbs",
    "types": [
        "fire"
    ],
    "stats": {
        "total": 250,
        "hp": 40,
        "attack": 40,
        "defense": 40,
        "sp. attack": 70,
        "sp. defense": 40,
        "speed": 20
    },
    "abilities": [
        {
            "name": "magma-armor",
            "effect": "Prevents freezing.",
            "hidden": false
        },
        {
            "name": "flame-body",
            "effect": "Has a 30% chance of burning attacking Pok\u00e9mon on contact.",
            "hidden": false
        },
        {
            "name": "weak-armor",
            "effect": "Raises Speed and lowers Defense by one stage each upon being hit by a physical move.",
            "hidden": true
        }
    ],
    "type_chart": {
        "2": [
            "ground",
            "rock",
            "water"
        ],
        "1": [
            "normal",
            "fighting",
            "flying",
            "poison",
            "ghost",
            "electric",
            "psychic",
            "dragon",
            "dark"
        ],
        "1/2": [
            "bug",
            "steel",
            "fire",
            "grass",
            "ice",
            "fairy"
        ],
        "0": [],
        "4": [],
        "1/4": []
    }
}