{
    "name": "mudkip",
    "id": 258,
    "height": "1'4\"",
    "weight": "16.8 lbs",
    "types": [
        "water"
    ],
    "stats": {
        "total": 310,
        "hp": 50,
        "attack": 70,
        "defense": 50,
        "sp. attack": 50,
        "sp. defense": 50,
        "speed": 40
    },
    "abilities": [
        {
            "name": "torrent",
            "effect": "Strengthens water moves to inflict 1.5\u00d7 damage at 1/3 max HP or less.",
            "hidden": false
        },
        {
            "name": "damp",
            "effect": "Prevents self destruct, explosion, and aftermath from working while the Pok\u00e9mon is in battle.",
            "hidden": true
        }
    ]
}