{
    "id": 283,
    "name": "surskit",
    "height": "1'8\"",
    "weight": "3.7 lbs",
    "types": [
        "bug",
        "water"
    ],
    "stats": {
        "total": 269,
        "hp": 40,
        "attack": 30,
        "defense": 32,
        "sp. attack": 50,
        "sp. defense": 52,
        "speed": 65
    },
    "abilities": [
        {
            "name": "swift-swim",
            "effect": "Doubles Speed during rain.",
            "hidden": false
        },
        {
            "name": "rain-dish",
            "effect": "Heals for 1/16 max HP after each turn during rain.",
            "hidden": true
        }
    ],
    "type_chart": {
        "4": [],
        "2": [
            "flying",
            "rock",
            "electric"
        ],
        "1": [
            "psychic",
            "normal",
            "ghost",
            "bug",
            "dragon",
            "dark",
            "poison",
            "fairy",
            "grass",
            "fire"
        ],
        "1/2": [
            "ground",
            "fighting",
            "water",
            "steel",
            "ice"
        ],
        "1/4": [],
        "0": []
    }
}