{
    "name": "palpitoad",
    "id": 536,
    "height": "2'7\"",
    "weight": "37.5 lbs",
    "types": [
        "water",
        "ground"
    ],
    "stats": {
        "total": 384,
        "hp": 75,
        "attack": 65,
        "defense": 55,
        "sp. attack": 65,
        "sp. defense": 55,
        "speed": 69
    },
    "abilities": [
        {
            "name": "swift-swim",
            "effect": "Doubles Speed during rain.",
            "hidden": false
        },
        {
            "name": "hydration",
            "effect": "Cures any major status ailment after each turn during rain.",
            "hidden": false
        },
        {
            "name": "water-absorb",
            "effect": "Absorbs water moves, healing for 1/4 max HP.",
            "hidden": true
        }
    ]
}