{
    "name": "eelektrik",
    "id": 603,
    "height": "3'11\"",
    "weight": "48.5 lbs",
    "types": [
        "electric"
    ],
    "stats": {
        "total": 405,
        "hp": 65,
        "attack": 85,
        "defense": 70,
        "sp. attack": 75,
        "sp. defense": 70,
        "speed": 40
    },
    "abilities": [
        {
            "name": "levitate",
            "effect": "Evades ground moves.",
            "hidden": false
        }
    ],
    "type_chart": {
        "2": [
            "ground"
        ],
        "1": [
            "normal",
            "fighting",
            "poison",
            "rock",
            "bug",
            "ghost",
            "fire",
            "water",
            "grass",
            "psychic",
            "ice",
            "dragon",
            "dark",
            "fairy"
        ],
        "1/2": [
            "flying",
            "steel",
            "electric"
        ],
        "0": [],
        "4": [],
        "1/4": []
    }
}