{
    "name": "crabrawler",
    "id": 739,
    "height": "1'12\"",
    "weight": "15.4 lbs",
    "types": [
        "fighting"
    ],
    "stats": {
        "total": 338,
        "hp": 47,
        "attack": 82,
        "defense": 57,
        "sp. attack": 42,
        "sp. defense": 47,
        "speed": 63
    },
    "abilities": [
        {
            "name": "hyper-cutter",
            "effect": "Prevents Attack from being lowered by other Pok\u00e9mon.",
            "hidden": false
        },
        {
            "name": "iron-fist",
            "effect": "Strengthens punch-based moves to 1.2\u00d7 their power.",
            "hidden": false
        },
        {
            "name": "anger-point",
            "effect": "Raises Attack to the maximum of six stages upon receiving a critical hit.",
            "hidden": true
        }
    ],
    "type_chart": {
        "2": [
            "flying",
            "psychic",
            "fairy"
        ],
        "1": [
            "normal",
            "fighting",
            "poison",
            "ground",
            "ghost",
            "steel",
            "fire",
            "water",
            "grass",
            "electric",
            "ice",
            "dragon"
        ],
        "1/2": [
            "rock",
            "bug",
            "dark"
        ],
        "0": []
    }
}