{
    "name": "bounsweet",
    "id": 761,
    "height": "0'12\"",
    "weight": "7.1 lbs",
    "types": [
        "grass"
    ],
    "stats": {
        "hp": 42,
        "attack": 30,
        "defense": 38,
        "sp. attack": 30,
        "sp. defense": 38,
        "speed": 32
    },
    "abilities": [
        {
            "name": "leaf-guard",
            "effect": "Protects against major status ailments during strong sunlight.",
            "hidden": false
        },
        {
            "name": "oblivious",
            "effect": "Prevents infatuation and protects against captivate.",
            "hidden": false
        },
        {
            "name": "sweet-veil",
            "effect": "Prevents friendly Pok\u00e9mon from sleeping.",
            "hidden": true
        }
    ]
}