{
    "name": "skwovet",
    "id": 819,
    "height": "0'12\"",
    "weight": "5.5 lbs",
    "types": [
        "normal"
    ],
    "stats": {
        "total": 275,
        "hp": 70,
        "attack": 55,
        "defense": 55,
        "sp. attack": 35,
        "sp. defense": 35,
        "speed": 25
    },
    "abilities": [
        {
            "name": "cheek-pouch",
            "effect": "Restores HP upon eating a Berry, in addition to the Berry's effect.",
            "hidden": false
        },
        {
            "name": "gluttony",
            "effect": "Makes the Pok\u00e9mon eat any held Berry triggered by low HP below 1/2 its max HP.",
            "hidden": true
        }
    ],
    "type_chart": {
        "2": [
            "fighting"
        ],
        "1": [
            "normal",
            "flying",
            "poison",
            "ground",
            "rock",
            "bug",
            "steel",
            "fire",
            "water",
            "grass",
            "electric",
            "psychic",
            "ice",
            "dragon",
            "dark",
            "fairy"
        ],
        "1/2": [],
        "0": [
            "ghost"
        ],
        "4": [],
        "1/4": []
    }
}